smallteacher/__init__.py
smallteacher/analysis.py
smallteacher/config.py
smallteacher/constants.py
smallteacher/data.py
smallteacher/pytorch_augmentations.py
smallteacher/utils.py
smallteacher/wbf.py
smallteacher/models/__init__.py
smallteacher/models/base.py
smallteacher/models/iou.py
smallteacher/models/semi_supervised.py
smallteacher/models/architectures/__init__.py
smallteacher/models/architectures/faster_rcnn.py
smallteacher/models/architectures/retinanet.py
smallteacher/models/architectures/ssd.py
smallteacher/models/architectures/yolo/__init__.py
smallteacher/models/architectures/yolo/yolo_config.py
smallteacher/models/architectures/yolo/yolo_layers.py
smallteacher/models/architectures/yolo/yolo_module.py
smallteacher-0.0.1.dist-info/LICENSE
smallteacher-0.0.1.dist-info/METADATA
smallteacher-0.0.1.dist-info/WHEEL
smallteacher-0.0.1.dist-info/top_level.txt
smallteacher-0.0.1.dist-info/RECORD
