Metadata-Version: 2.1
Name: smallteacher
Version: 0.0.1
Summary: Research codebase for teacher-student based semi-supervised object detection in agricultural settings
Home-page: https://github.com/smallrobotcompany/smallteacher
Author: Gabriel Tseng
Author-email: gabrieltseng95@gmail.com
Classifier: Programming Language :: Python :: 3
Classifier: License :: Other/Proprietary License
Classifier: Operating System :: OS Independent
Requires-Python: >=3.8
License-File: LICENSE
Requires-Dist: protobuf (==3.20.1)
Requires-Dist: tqdm (>=4.61.1)
Requires-Dist: torch (>=1.11.0)
Requires-Dist: torchvision (>=0.12.0)
Requires-Dist: pytorch-lightning (==1.6.1)
